CHANGES.txt
MANIFEST.in
README.txt
enumlike.py
setup.cfg
setup.py
enumlike.egg-info/PKG-INFO
enumlike.egg-info/SOURCES.txt
enumlike.egg-info/dependency_links.txt
enumlike.egg-info/entry_points.txt
enumlike.egg-info/not-zip-safe
enumlike.egg-info/top_level.txt