Metadata-Version: 1.1
Name: enumlike
Version: 0.2
Summary: An enum like object for using django-form-choces.
Home-page: https://github.com/oyakata/enumlike
Author: imagawa_yakata(oyakata)
Author-email: imagawa.hougikumaru@gmail.com
License: MIT
Platform: UNKNOWN
Classifier: Intended Audience :: Developers
Classifier: Programming Language :: Python
Classifier: License :: OSI Approved :: MIT License
